cryptex_tools/__init__.py
cryptex_tools/__main__.py
cryptex_tools/ciphers/__init__.py
cryptex_tools/ciphers/affine.py
cryptex_tools/ciphers/atbash.py
cryptex_tools/ciphers/caesar.py
cryptex_tools/ciphers/keyboard_shift.py
cryptex_tools/ciphers/pigpen.py
cryptex_tools/ciphers/playfair.py
cryptex_tools/ciphers/railfence.py
cryptex_tools/ciphers/rot13.py
cryptex_tools/ciphers/vigenere.py
cryptex_tools/cli/__init__.py
cryptex_tools/cli/main.py
cryptex_tools/cryptanalysis/__init__.py
cryptex_tools/cryptanalysis/brute_force_caesar.py
cryptex_tools/cryptanalysis/frequency_analysis.py
cryptex_tools/cryptanalysis/keywordlist.txt
cryptex_tools/cryptanalysis/vigenere_crack.py
cryptex_tools/utils/__init__.py
cryptex_tools/utils/cipher_loader.py
cryptex_tools-0.1.1.dist-info/licenses/LICENSE
cryptex_tools-0.1.1.dist-info/METADATA
cryptex_tools-0.1.1.dist-info/WHEEL
cryptex_tools-0.1.1.dist-info/entry_points.txt
cryptex_tools-0.1.1.dist-info/top_level.txt
cryptex_tools-0.1.1.dist-info/RECORD
