Metadata-Version: 2.4
Name: cryptex_tools
Version: 0.1.1
Summary: An educational toolkit for classic ciphers and cryptanalysis
Author-email: Arpit Omprakash <omprakasharpit@gmail.com>
License-Expression: MIT
Project-URL: Homepage, https://github.com/arpit-omprakash/cryptex-tools
Classifier: Development Status :: 3 - Alpha
Classifier: Intended Audience :: Education
Classifier: Programming Language :: Python :: 3
Classifier: Topic :: Security :: Cryptography
Requires-Python: >=3.7
License-File: LICENSE
Requires-Dist: click>=8.0
Dynamic: license-file
